splitml/__init__.py
splitml/constants.py
splitml/groupers.py
splitml/html_splitter.py
splitml/pdf_splitter.py
splitml/splitml.py
splitml/stats.py
splitml/text_splitter.py
splitml-0.5.3.dist-info/LICENSE
splitml-0.5.3.dist-info/METADATA
splitml-0.5.3.dist-info/WHEEL
splitml-0.5.3.dist-info/top_level.txt
splitml-0.5.3.dist-info/RECORD
