Metadata-Version: 2.1
Name: splitml
Version: 0.5.3
Summary: Split Markup Language (HTML and Markdown) to Groups and Nodes
Author: Hansimov
Project-URL: Homepage, https://github.com/Hansimov/splitml
Project-URL: Issues, https://github.com/Hansimov/splitml/issues
Classifier: Programming Language :: Python :: 3
Classifier: License :: OSI Approved :: MIT License
Classifier: Operating System :: OS Independent
Requires-Python: >=3.6
License-File: LICENSE
Requires-Dist: purehtml
Requires-Dist: markdown2
Requires-Dist: beautifulsoup4
Requires-Dist: tiktoken
Requires-Dist: PyMuPDF
